supervisor_ext-0.1.5-py2.7-nspkg.pth
supervisor_ext/command_line.py
supervisor_ext/controllerplugin.py
supervisor_ext/memorycheck.py
supervisor_ext/rpcinterface.py
supervisor_ext-0.1.5.dist-info/METADATA
supervisor_ext-0.1.5.dist-info/RECORD
supervisor_ext-0.1.5.dist-info/WHEEL
supervisor_ext-0.1.5.dist-info/entry_points.txt
supervisor_ext-0.1.5.dist-info/namespace_packages.txt
supervisor_ext-0.1.5.dist-info/top_level.txt
